Metadata-Version: 1.1
Name: coollib
Version: 0.0.4
Summary: Nothing & Everything Library, coming soon.
Home-page: UNKNOWN
Author: aTq_
Author-email: UNKNOWN
License: MIT
Keywords: cool
Platform: UNKNOWN
Classifier: Development Status :: 5 - Production/Stable
Classifier: Intended Audience :: Education
Classifier: Operating System :: Microsoft :: Windows :: Windows 10
Classifier: License :: OSI Approved :: MIT License
Classifier: Programming Language :: Python :: 3
